{"ongoing_trials": {}, "hyperparameters": {"space": [{"class_name": "Choice", "config": {"name": "num_layers", "default": 2, "conditions": [], "values": [2, 3, 4], "ordered": true}}, {"class_name": "Choice", "config": {"name": "optimizer", "default": "Adam", "conditions": [], "values": ["Adam", "Adagrad", "Nadam"], "ordered": false}}, {"class_name": "Float", "config": {"name": "learning_rate", "default": 0.0001, "conditions": [], "min_value": 0.0001, "max_value": 0.1, "step": null, "sampling": "log"}}, {"class_name": "Int", "config": {"name": "lstm_units_1", "default": null, "conditions": [], "min_value": 32, "max_value": 128, "step": 32, "sampling": "linear"}}, {"class_name": "Choice", "config": {"name": "activation_1", "default": "tanh", "conditions": [], "values": ["tanh", "sigmoid", "linear"], "ordered": false}}, {"class_name": "Float", "config": {"name": "dropout_1", "default": 0.1, "conditions": [], "min_value": 0.1, "max_value": 0.3, "step": 0.1, "sampling": "linear"}}, {"class_name": "Choice", "config": {"name": "lstm_units_2", "default": 32, "conditions": [], "values": [32], "ordered": true}}, {"class_name": "Choice", "config": {"name": "activation_2", "default": "tanh", "conditions": [], "values": ["tanh", "sigmoid", "linear"], "ordered": false}}, {"class_name": "Float", "config": {"name": "dropout_2", "default": 0.1, "conditions": [], "min_value": 0.1, "max_value": 0.3, "step": 0.1, "sampling": "linear"}}, {"class_name": "Choice", "config": {"name": "lstm_units_3", "default": 32, "conditions": [], "values": [32], "ordered": true}}, {"class_name": "Choice", "config": {"name": "activation_3", "default": "tanh", "conditions": [], "values": ["tanh", "sigmoid", "linear"], "ordered": false}}, {"class_name": "Float", "config": {"name": "dropout_3", "default": 0.1, "conditions": [], "min_value": 0.1, "max_value": 0.3, "step": 0.1, "sampling": "linear"}}, {"class_name": "Choice", "config": {"name": "lstm_units_4", "default": 32, "conditions": [], "values": [32], "ordered": true}}, {"class_name": "Choice", "config": {"name": "activation_4", "default": "tanh", "conditions": [], "values": ["tanh", "sigmoid", "linear"], "ordered": false}}, {"class_name": "Float", "config": {"name": "dropout_4", "default": 0.1, "conditions": [], "min_value": 0.1, "max_value": 0.3, "step": 0.1, "sampling": "linear"}}], "values": {"num_layers": 2, "optimizer": "Adam", "learning_rate": 0.0001, "lstm_units_1": 32, "activation_1": "tanh", "dropout_1": 0.1, "lstm_units_2": 32, "activation_2": "tanh", "dropout_2": 0.1, "lstm_units_3": 32, "activation_3": "tanh", "dropout_3": 0.1, "lstm_units_4": 32, "activation_4": "tanh", "dropout_4": 0.1}}, "start_order": ["00", "01", "02", "03", "04", "05", "06", "07", "08", "09", "10", "11", "12", "13", "14", "15", "16", "17", "18", "19"], "end_order": ["00", "01", "02", "03", "04", "05", "06", "07", "08", "09", "10", "11", "12", "13", "14", "15", "16", "17", "18", "19"], "run_times": {"00": 1, "01": 1, "02": 1, "03": 1, "04": 1, "05": 1, "06": 1, "07": 1, "08": 1, "09": 1, "10": 1, "11": 1, "12": 1, "13": 1, "14": 1, "15": 1, "16": 1, "17": 1, "18": 1, "19": 1}, "retry_queue": [], "seed": 8094, "seed_state": 8385, "tried_so_far": ["439d62cf3c2e25e19f7ef049a2847bf9", "6ad8b013135420919926b8ecf78ebbab", "2816a1dbe573a2657d40cfd2f13ed1c1", "83afdec4eba2ea2e2b5dbfcc648b521f", "ed21dd603696a6eedb9aa0080df17893", "2c3e40ad6074e0696ea37309a933ab59", "a71d1bfc9e6e18e621336a178de4de55", "adb62c6ba4b2e13ac46a1decf7289e05", "07f56a410be825450fa993e66c19c86e", "6aa3991ab1e8a5f240e499d2f8ab1892", "72e674e3a6c78b09dba657aec86ef2d6", "3336c186feda6a547183fe40cc329126", "972bde251088238793ab4205190e7825", "b0b82285a5573dec19f9ed1f9a718800", "3726e95eadf241ed9dac0f096f17d218", "e1f8860afdd55a21ab3ded8959b4363c", "b2997b208a6b24890473a9dec563c542", "5017dd67924aa10e0d0d5f9cf8b842bd", "2533fe96c628ff0d15d2b87a766264fd", "a70c82c0d06b54ca4c9cf9f00aa73a64"], "id_to_hash": {"00": "3336c186feda6a547183fe40cc329126", "01": "adb62c6ba4b2e13ac46a1decf7289e05", "02": "3726e95eadf241ed9dac0f096f17d218", "03": "07f56a410be825450fa993e66c19c86e", "04": "a71d1bfc9e6e18e621336a178de4de55", "05": "ed21dd603696a6eedb9aa0080df17893", "06": "b2997b208a6b24890473a9dec563c542", "07": "6aa3991ab1e8a5f240e499d2f8ab1892", "08": "2c3e40ad6074e0696ea37309a933ab59", "09": "439d62cf3c2e25e19f7ef049a2847bf9", "10": "a70c82c0d06b54ca4c9cf9f00aa73a64", "11": "5017dd67924aa10e0d0d5f9cf8b842bd", "12": "6ad8b013135420919926b8ecf78ebbab", "13": "e1f8860afdd55a21ab3ded8959b4363c", "14": "83afdec4eba2ea2e2b5dbfcc648b521f", "15": "72e674e3a6c78b09dba657aec86ef2d6", "16": "2816a1dbe573a2657d40cfd2f13ed1c1", "17": "972bde251088238793ab4205190e7825", "18": "2533fe96c628ff0d15d2b87a766264fd", "19": "b0b82285a5573dec19f9ed1f9a718800"}, "display": {"search_start": "2025-04-02T12:57:26.906181", "trial_start": {"00": "2025-04-02T12:57:26.906181", "01": "2025-04-02T12:57:46.744807", "02": "2025-04-02T12:58:09.084544", "03": "2025-04-02T12:58:27.743858", "04": "2025-04-02T12:58:47.849491", "05": "2025-04-02T12:59:08.500368", "06": "2025-04-02T12:59:26.952762", "07": "2025-04-02T12:59:44.529981", "08": "2025-04-02T13:00:02.155290", "09": "2025-04-02T13:00:24.195404", "10": "2025-04-02T13:00:43.688742", "11": "2025-04-02T13:01:07.093036", "12": "2025-04-02T13:01:29.891571", "13": "2025-04-02T13:01:52.791301", "14": "2025-04-02T13:02:15.975852", "15": "2025-04-02T13:02:37.618974", "16": "2025-04-02T13:02:59.452822", "17": "2025-04-02T13:03:22.337524", "18": "2025-04-02T13:03:41.672942", "19": "2025-04-02T13:04:02.640735"}, "trial_number": {"00": 1, "01": 2, "02": 3, "03": 4, "04": 5, "05": 6, "06": 7, "07": 8, "08": 9, "09": 10, "10": 11, "11": 12, "12": 13, "13": 14, "14": 15, "15": 16, "16": 17, "17": 18, "18": 19, "19": 20}}, "num_initial_points": null, "alpha": 0.0001, "beta": 2.6}