{"trial_id": "00", "hyperparameters": {"space": [{"class_name": "Choice", "config": {"name": "num_layers", "default": 2, "conditions": [], "values": [2, 3, 4], "ordered": true}}, {"class_name": "Choice", "config": {"name": "optimizer", "default": "Adam", "conditions": [], "values": ["Adam", "Adagrad", "Nadam"], "ordered": false}}, {"class_name": "Float", "config": {"name": "learning_rate", "default": 0.0001, "conditions": [], "min_value": 0.0001, "max_value": 0.1, "step": null, "sampling": "log"}}, {"class_name": "Int", "config": {"name": "lstm_units_1", "default": null, "conditions": [], "min_value": 32, "max_value": 128, "step": 32, "sampling": "linear"}}, {"class_name": "Choice", "config": {"name": "activation_1", "default": "tanh", "conditions": [], "values": ["tanh", "sigmoid", "linear"], "ordered": false}}, {"class_name": "Float", "config": {"name": "dropout_1", "default": 0.1, "conditions": [], "min_value": 0.1, "max_value": 0.3, "step": 0.1, "sampling": "linear"}}, {"class_name": "Choice", "config": {"name": "lstm_units_2", "default": 32, "conditions": [], "values": [32], "ordered": true}}, {"class_name": "Choice", "config": {"name": "activation_2", "default": "tanh", "conditions": [], "values": ["tanh", "sigmoid", "linear"], "ordered": false}}, {"class_name": "Float", "config": {"name": "dropout_2", "default": 0.1, "conditions": [], "min_value": 0.1, "max_value": 0.3, "step": 0.1, "sampling": "linear"}}, {"class_name": "Choice", "config": {"name": "lstm_units_3", "default": 32, "conditions": [], "values": [32], "ordered": true}}, {"class_name": "Choice", "config": {"name": "activation_3", "default": "tanh", "conditions": [], "values": ["tanh", "sigmoid", "linear"], "ordered": false}}, {"class_name": "Float", "config": {"name": "dropout_3", "default": 0.1, "conditions": [], "min_value": 0.1, "max_value": 0.3, "step": 0.1, "sampling": "linear"}}, {"class_name": "Choice", "config": {"name": "lstm_units_4", "default": 32, "conditions": [], "values": [32], "ordered": true}}, {"class_name": "Choice", "config": {"name": "activation_4", "default": "tanh", "conditions": [], "values": ["tanh", "sigmoid", "linear"], "ordered": false}}, {"class_name": "Float", "config": {"name": "dropout_4", "default": 0.1, "conditions": [], "min_value": 0.1, "max_value": 0.3, "step": 0.1, "sampling": "linear"}}], "values": {"num_layers": 4, "optimizer": "Adagrad", "learning_rate": 0.003954245484900361, "lstm_units_1": 32, "activation_1": "tanh", "dropout_1": 0.2, "lstm_units_2": 32, "activation_2": "tanh", "dropout_2": 0.2, "lstm_units_3": 32, "activation_3": "tanh", "dropout_3": 0.1, "lstm_units_4": 32, "activation_4": "tanh", "dropout_4": 0.1}}, "metrics": {"metrics": {"loss": {"direction": "min", "observations": [{"value": [0.00018207344692200422], "step": 0}]}, "root_mean_squared_error": {"direction": "min", "observations": [{"value": [0.013493459671735764], "step": 0}]}, "val_loss": {"direction": "min", "observations": [{"value": [0.00014925871801096946], "step": 0}]}, "val_root_mean_squared_error": {"direction": "min", "observations": [{"value": [0.012217148207128048], "step": 0}]}}}, "score": 0.00014925871801096946, "best_step": 0, "status": "COMPLETED", "message": null}